{"v":5,"entries":{"rmappclip--docs":{"id":"rmappclip--docs","title":"RMAppClip","name":"Docs","importPath":"./src/rm-app-clip/rm-app-clip.stories.tsx","type":"docs","tags":["dev","test","manifest","autodocs"],"storiesImports":[]},"rmappclip--basic":{"type":"story","subtype":"story","id":"rmappclip--basic","name":"Basic","title":"RMAppClip","importPath":"./src/rm-app-clip/rm-app-clip.stories.tsx","componentPath":"./src/rm-app-clip/rm-app-clip.tsx","tags":["dev","test","manifest","autodocs"],"exportName":"Basic"},"rmenvbadge--docs":{"id":"rmenvbadge--docs","title":"RMEnvBadge","name":"Docs","importPath":"./src/rm-env-badge/rm-env-badge.stories.tsx","type":"docs","tags":["dev","test","manifest","autodocs"],"storiesImports":[]},"rmenvbadge--basic":{"type":"story","subtype":"story","id":"rmenvbadge--basic","name":"Basic","title":"RMEnvBadge","importPath":"./src/rm-env-badge/rm-env-badge.stories.tsx","componentPath":"./src/rm-env-badge/rm-env-badge.tsx","tags":["dev","test","manifest","autodocs"],"exportName":"Basic"},"rmerrorboundary--docs":{"id":"rmerrorboundary--docs","title":"RMErrorBoundary","name":"Docs","importPath":"./src/rm-error-boundary/rm-error-boundary.stories.tsx","type":"docs","tags":["dev","test","manifest","autodocs"],"storiesImports":[]},"rmerrorboundary--basic":{"type":"story","subtype":"story","id":"rmerrorboundary--basic","name":"Basic","title":"RMErrorBoundary","importPath":"./src/rm-error-boundary/rm-error-boundary.stories.tsx","componentPath":"./src/rm-error-boundary/rm-error-boundary.tsx","tags":["dev","test","manifest","autodocs"],"exportName":"Basic"},"rmlabelledsegmentedcontrol--docs":{"id":"rmlabelledsegmentedcontrol--docs","title":"RMLabelledSegmentedControl","name":"Docs","importPath":"./src/rm-labelled-segmented-control/rm-labelled-segmented-control.stories.tsx","type":"docs","tags":["dev","test","manifest","autodocs"],"storiesImports":[]},"rmlabelledsegmentedcontrol--basic":{"type":"story","subtype":"story","id":"rmlabelledsegmentedcontrol--basic","name":"Basic","title":"RMLabelledSegmentedControl","importPath":"./src/rm-labelled-segmented-control/rm-labelled-segmented-control.stories.tsx","componentPath":"./src/rm-labelled-segmented-control/rm-labelled-segmented-control.tsx","tags":["dev","test","manifest","autodocs"],"exportName":"Basic"},"rmlabelledslider--docs":{"id":"rmlabelledslider--docs","title":"RMLabelledSlider","name":"Docs","importPath":"./src/rm-labelled-slider/rm-labelled-slider.stories.tsx","type":"docs","tags":["dev","test","manifest","autodocs"],"storiesImports":[]},"rmlabelledslider--basic":{"type":"story","subtype":"story","id":"rmlabelledslider--basic","name":"Basic","title":"RMLabelledSlider","importPath":"./src/rm-labelled-slider/rm-labelled-slider.stories.tsx","componentPath":"./src/rm-labelled-slider/rm-labelled-slider.tsx","tags":["dev","test","manifest","autodocs"],"exportName":"Basic"},"rmlayout--docs":{"id":"rmlayout--docs","title":"RMLayout","name":"Docs","importPath":"./src/rm-layout/rm-layout.stories.tsx","type":"docs","tags":["dev","test","manifest","autodocs"],"storiesImports":[]},"rmlayout--basic":{"type":"story","subtype":"story","id":"rmlayout--basic","name":"Basic","title":"RMLayout","importPath":"./src/rm-layout/rm-layout.stories.tsx","tags":["dev","test","manifest","autodocs"],"exportName":"Basic"},"rmmantineprovider-checkbox--checkbox":{"type":"story","subtype":"story","id":"rmmantineprovider-checkbox--checkbox","name":"Checkbox","title":"RMMantineProvider/Checkbox","importPath":"./src/rm-mantine-provider/stories/checkbox.stories.tsx","componentPath":"./node_modules/@mantine/core/esm/index.mjs","tags":["dev","test","manifest"],"exportName":"Checkbox"},"rmmantineprovider-textinput--text-input":{"type":"story","subtype":"story","id":"rmmantineprovider-textinput--text-input","name":"Text Input","title":"RMMantineProvider/TextInput","importPath":"./src/rm-mantine-provider/stories/input.stories.tsx","componentPath":"./node_modules/@mantine/core/esm/index.mjs","tags":["dev","test","manifest"],"exportName":"TextInput"},"rmmantineprovider-modal--modal":{"type":"story","subtype":"story","id":"rmmantineprovider-modal--modal","name":"Modal","title":"RMMantineProvider/Modal","importPath":"./src/rm-mantine-provider/stories/modal.stories.tsx","componentPath":"./node_modules/@mantine/core/esm/index.mjs","tags":["dev","test","manifest"],"exportName":"Modal"},"rmmantineprovider-slider--slider":{"type":"story","subtype":"story","id":"rmmantineprovider-slider--slider","name":"Slider","title":"RMMantineProvider/Slider","importPath":"./src/rm-mantine-provider/stories/slider.stories.tsx","componentPath":"./node_modules/@mantine/core/esm/index.mjs","tags":["dev","test","manifest"],"exportName":"Slider"},"rmmantineprovider-switch--switch":{"type":"story","subtype":"story","id":"rmmantineprovider-switch--switch","name":"Switch","title":"RMMantineProvider/Switch","importPath":"./src/rm-mantine-provider/stories/switch.stories.tsx","componentPath":"./node_modules/@mantine/core/esm/index.mjs","tags":["dev","test","manifest"],"exportName":"Switch"},"rmsidepanel--docs":{"id":"rmsidepanel--docs","title":"RMSidePanel","name":"Docs","importPath":"./src/rm-side-panel/rm-side-panel.stories.tsx","type":"docs","tags":["dev","test","manifest","autodocs"],"storiesImports":[]},"rmsidepanel--basic":{"type":"story","subtype":"story","id":"rmsidepanel--basic","name":"Basic","title":"RMSidePanel","importPath":"./src/rm-side-panel/rm-side-panel.stories.tsx","componentPath":"./src/rm-side-panel/rm-side-panel.tsx","tags":["dev","test","manifest","autodocs"],"exportName":"Basic"},"rmthemebutton--docs":{"id":"rmthemebutton--docs","title":"RMThemeButton","name":"Docs","importPath":"./src/rm-theme-button/rm-theme-button.stories.tsx","type":"docs","tags":["dev","test","manifest","autodocs"],"storiesImports":[]},"rmthemebutton--basic":{"type":"story","subtype":"story","id":"rmthemebutton--basic","name":"Basic","title":"RMThemeButton","importPath":"./src/rm-theme-button/rm-theme-button.stories.tsx","componentPath":"./src/rm-theme-button/rm-theme-button.tsx","tags":["dev","test","manifest","autodocs"],"exportName":"Basic"}}}